{
"skeleton": { "hash": "ZhGhwQK2Jnz9rx0MhpcKhB/dcPc", "spine": "3.6.53", "width": 559.15, "height": 447.32, "images": "./images/jump dust fx/" },
"bones": [
	{ "name": "root", "x": -15.78, "scaleX": -2.11, "scaleY": 2.11 }
],
"slots": [
	{ "name": "jump dust fx", "bone": "root", "color": "e89352ff", "attachment": "1", "blend": "additive" }
],
"skins": {
	"default": {
		"jump dust fx": {
			"1": { "x": 29.5, "y": 64, "width": 265, "height": 212 },
			"2": { "x": 33.5, "y": 82, "width": 271, "height": 250 },
			"3": { "x": 39.5, "y": 98.5, "width": 283, "height": 285 },
			"4": { "x": 39, "y": 96.5, "width": 282, "height": 281 },
			"5": { "x": 39, "y": 99.5, "width": 282, "height": 289 },
			"6": { "x": 41, "y": 141.5, "width": 286, "height": 373 },
			"7": { "x": 66.5, "y": 147, "width": 339, "height": 384 },
			"8": { "x": 65, "y": 146, "width": 342, "height": 380 },
			"9": { "x": 56.5, "y": 151, "width": 335, "height": 390 },
			"10": { "x": 50, "y": 156, "width": 348, "height": 392 },
			"11": { "x": 47.5, "y": 156.5, "width": 347, "height": 383 },
			"12": { "x": 45, "y": 153.5, "width": 360, "height": 385 },
			"13": { "x": 22.5, "y": 156.5, "width": 405, "height": 377 },
			"14": { "x": 43, "y": 158, "width": 368, "height": 376 },
			"15": { "x": 43.5, "y": 165, "width": 371, "height": 376 },
			"16": { "x": 46.5, "y": 165.5, "width": 373, "height": 373 },
			"17": { "x": 48.5, "y": 166, "width": 381, "height": 372 },
			"18": { "x": 50, "y": 171, "width": 384, "height": 372 },
			"19": { "x": 49.5, "y": 176.5, "width": 387, "height": 363 },
			"20": { "x": 48, "y": 179, "width": 384, "height": 364 },
			"21": { "x": 47.5, "y": 181, "width": 387, "height": 366 },
			"22": { "x": 47, "y": 198, "width": 386, "height": 334 },
			"23": { "x": 57, "y": 201, "width": 368, "height": 334 },
			"24": { "x": 59, "y": 202.5, "width": 368, "height": 335 },
			"25": { "x": 98, "y": 302, "width": 120, "height": 142 },
			"26": { "x": 74.5, "y": 336, "width": 77, "height": 72 },
			"27": { "x": 73.5, "y": 336.5, "width": 79, "height": 71 },
			"28": { "x": 67.5, "y": 337, "width": 59, "height": 70 },
			"29": { "x": 64.5, "y": 357.5, "width": 47, "height": 29 },
			"30": { "x": 49.5, "y": 368, "width": 13, "height": 12 }
		}
	}
},
"animations": {
	"fx": {
		"slots": {
			"jump dust fx": {
				"color": [
					{ "time": 0.5, "color": "e89252ff" },
					{ "time": 1, "color": "e8915200" }
				],
				"attachment": [
					{ "time": 0, "name": "1" },
					{ "time": 0.0333, "name": "2" },
					{ "time": 0.0667, "name": "3" },
					{ "time": 0.1, "name": "4" },
					{ "time": 0.1333, "name": "5" },
					{ "time": 0.1667, "name": "6" },
					{ "time": 0.2, "name": "7" },
					{ "time": 0.2333, "name": "8" },
					{ "time": 0.2667, "name": "9" },
					{ "time": 0.3, "name": "10" },
					{ "time": 0.3333, "name": "11" },
					{ "time": 0.3667, "name": "12" },
					{ "time": 0.4, "name": "13" },
					{ "time": 0.4333, "name": "14" },
					{ "time": 0.4667, "name": "15" },
					{ "time": 0.5, "name": "16" },
					{ "time": 0.5333, "name": "17" },
					{ "time": 0.5667, "name": "18" },
					{ "time": 0.6, "name": "19" },
					{ "time": 0.6333, "name": "20" },
					{ "time": 0.6667, "name": "21" },
					{ "time": 0.7, "name": "22" },
					{ "time": 0.7333, "name": "23" },
					{ "time": 0.7667, "name": "24" },
					{ "time": 0.8, "name": "25" },
					{ "time": 0.8333, "name": "26" },
					{ "time": 0.8667, "name": "27" },
					{ "time": 0.9, "name": "28" },
					{ "time": 0.9333, "name": "29" },
					{ "time": 0.9667, "name": "30" },
					{ "time": 1, "name": null }
				]
			}
		},
		"bones": {
			"root": {
				"rotate": [
					{ "time": 0.1333, "angle": 7.85 }
				],
				"translate": [
					{ "time": 0.1333, "x": 0, "y": 26.74 }
				],
				"scale": [
					{ "time": 0.1333, "x": 1, "y": 1.582 }
				]
			}
		}
	}
}
}